[
    {
      "title": "ข้อใดคือสัตว์ที่ออกลูกเป็นตัว?",
      "options": [
        "เต่า",
        "จระเข้",
        "แมว",
        "ไก่"
      ],
      "answer": 3
    },
    {
      "title": "ข้อใดเป็นดาวเคราะห์ดวงที่ใหญ่ที่สุดในระบบสุริยะ?",
      "options": [
        "ดาวพฤหัสบดี",
        "ดาวเสาร์",
        "ดาวศุกร์",
        "ดาวอังคาร"
      ],
      "answer": 1
    },
    {
      "title": "วรรณกรรมเรื่อง 'สามก๊ก' มีต้นกำเนิดจากประเทศใด?",
      "options": [
        "ญี่ปุ่น",
        "เกาหลี",
        "จีน",
        "เวียดนาม"
      ],
      "answer": 3
    },
    {
      "title": "ธนบัตรชนิดใดมีมูลค่ามากที่สุดในประเทศไทย?",
      "options": [
        "1,000 บาท",
        "500 บาท",
        "100 บาท",
        "50 บาท"
      ],
      "answer": 1
    },
    {
      "title": "ข้อใดคือองค์ประกอบที่มีมากที่สุดในเปลือกโลก?",
      "options": [
        "เหล็ก",
        "ออกซิเจน",
        "ซิลิคอน",
        "แคลเซียม"
      ],
      "answer": 2
    },
    {
      "title": "กีฬาชนิดใดที่ใช้ลูกขนไก่ในการแข่งขัน?",
      "options": [
        "เทนนิส",
        "แบดมินตัน",
        "ฟุตบอล",
        "กอล์ฟ"
      ],
      "answer": 2
    },
    {
      "title": "ข้อใดคือเมืองที่ได้ชื่อว่าเป็น 'นครแห่งเทวดา'?",
      "options": [
        "เชียงใหม่",
        "กรุงเทพมหานคร",
        "พัทยา",
        "ภูเก็ต"
      ],
      "answer": 2
    },
    {
      "title": "ข้อใดเป็นแร่ธาตุที่มีความแข็งที่สุดในธรรมชาติ?",
      "options": [
        "เพชร",
        "ทองคำ",
        "เหล็ก",
        "ควอตซ์"
      ],
      "answer": 1
    },
    {
      "title": "อวัยวะใดในร่างกายมนุษย์ทำหน้าที่สูบฉีดโลหิต?",
      "options": [
        "ตับ",
        "ปอด",
        "ไต",
        "หัวใจ"
      ],
      "answer": 4
    },
    {
      "title": "ข้อใดเป็นชื่อของสารที่ทำให้พืชมีสีเขียว?",
      "options": [
        "คลอโรฟิลล์",
        "เฮโมโกลบิน",
        "คาร์โบไฮเดรต",
        "แคลเซียม"
      ],
      "answer": 1
    },
    {
      "title": "ข้อใดคือมหาสมุทรที่ใหญ่ที่สุดในโลก?",
      "options": [
        "มหาสมุทรแอตแลนติก",
        "มหาสมุทรอินเดีย",
        "มหาสมุทรอาร์กติก",
        "มหาสมุทรแปซิฟิก"
      ],
      "answer": 4
    },
    {
      "title": "ข้อใดเป็นอุปกรณ์ที่ใช้ในการวัดอุณหภูมิ?",
      "options": [
        "บารอมิเตอร์",
        "โทรทัศน์",
        "เทอร์โมมิเตอร์",
        "เครื่องชั่งน้ำหนัก"
      ],
      "answer": 3
    },
    {
      "title": "ข้อใดคือธาตุที่เป็นองค์ประกอบหลักของน้ำ?",
      "options": [
        "ออกซิเจนและคาร์บอน",
        "ไฮโดรเจนและออกซิเจน",
        "ไนโตรเจนและไฮโดรเจน",
        "โซเดียมและคลอรีน"
      ],
      "answer": 2
    },
    {
      "title": "ข้อใดคือประเทศที่มีพื้นที่มากที่สุดในโลก?",
      "options": [
        "สหรัฐอเมริกา",
        "จีน",
        "รัสเซีย",
        "แคนาดา"
      ],
      "answer": 3
    },
    {
      "title": "สัตว์ชนิดใดมีขนาดใหญ่ที่สุดในโลก?",
      "options": [
        "วาฬสีน้ำเงิน",
        "ช้างแอฟริกา",
        "จระเข้",
        "ปลาฉลามขาว"
      ],
      "answer": 1
    },
    {
      "title": "ข้อใดเป็นประเทศที่ตั้งอยู่ในทวีปอเมริกาใต้?",
      "options": [
        "แคนาดา",
        "บราซิล",
        "อิตาลี",
        "ออสเตรเลีย"
      ],
      "answer": 2
    },
    {
      "title": "ข้อใดคือวิชาเกี่ยวกับการศึกษาเกี่ยวกับดวงดาวและจักรวาล?",
      "options": [
        "ธรณีวิทยา",
        "ฟิสิกส์",
        "ดาราศาสตร์",
        "ชีววิทยา"
      ],
      "answer": 3
    },
    {
      "title": "ข้อใดคือชื่อของทวีปที่มีประชากรมากที่สุดในโลก?",
      "options": [
        "แอฟริกา",
        "เอเชีย",
        "ยุโรป",
        "อเมริกาเหนือ"
      ],
      "answer": 2
    },
    {
      "title": "ข้อใดคือชื่อของทะเลสาบที่ใหญ่ที่สุดในโลก?",
      "options": [
        "ทะเลสาบแคสเปียน",
        "ทะเลสาบสุพีเรีย",
        "ทะเลสาบไบคาล",
        "ทะเลสาบวิคตอเรีย"
      ],
      "answer": 1
    },
    {
      "title": "ข้อใดคือสิ่งที่พืชต้องใช้ในการสังเคราะห์แสง?",
      "options": [
        "น้ำ",
        "ดิน",
        "แสงแดด",
        "อากาศ"
      ],
      "answer": 3
    }
  ]
  
